{
    "nodes": [{
            "id": 0,
            "category": "circle",
            "i": 0,
            "j": 3,
            "text": "Start"
        },
        {
            "id": 1,
            "category": "rect",
            "i": 1,
            "j": 1,
            "text": "Beilfuss"
        },
        {
            "id": 2,
            "category": "rect",
            "i": 1,
            "j": 2,
            "text": "Ceil"
        },
        {
            "id": 3,
            "category": "rect",
            "i": 1,
            "j": 3,
            "text": "Floor"
        },
        {
            "id": 4,
            "category": "rect",
            "i": 2,
            "j": 1,
            "text": "Caps"
        },
        {
            "id": 5,
            "category": "rect",
            "i": 2,
            "j": 3,
            "text": "Candy"
        },
        {
            "id": 51,
            "category": "rect",
            "i": 2,
            "j": 4,
            "text": "Soda"
        },
        {
            "id": 52,
            "category": "rect",
            "i": 2,
            "j": 5,
            "text": "Market"
        },
        {
            "id": 16,
            "category": "rect",
            "i": 3,
            "j": 2,
            "text": "Beside"
        },
        {
            "id": 6,
            "category": "rect",
            "i": 3,
            "j": 3,
            "text": "Crush"
        },
        {
            "id": 7,
            "category": "rect",
            "i": 4,
            "j": 3,
            "text": "Pause"
        },
        {
            "id": 8,
            "category": "rect",
            "i": 5,
            "j": 3,
            "text": "Jeffery"
        },
        {
            "id": 9,
            "category": "rect",
            "i": 6,
            "j": 3,
            "text": "Joking"
        },
        {
            "id": 10,
            "category": "circle",
            "i": 7,
            "j": 3,
            "text": "End"
        }
    ],
    "links": [
        {
            "from": 0,
            "to": 1
        },
        {
            "from": 0,
            "to": 2            
        },
        {
            "from": 0,
            "to": 3
        },
        {
            "from": 3,
            "to": 4
        },
        {
            "from": 3,
            "to": 1
        },
        {
            "from": 3,
            "to": 2
        },
        {
            "from": 3,
            "to": 5            
        },
        {
            "from": 3,
            "to": 16            
        },
        {
            "from": 5,
            "to": 6
        },
        {
            "from": 6,
            "to": 7
        },
        {
            "from": 6,
            "to": 8
        },
        {
            "from": 7,
            "to": 8
        },
        {
            "from": 8,
            "to": 9
        },
        {
            "from": 9,
            "to": 10            
        },
        {
            "from": 5,
            "to": 51            
        },        
        {
            "from": 5,
            "to": 52            
        },        
        {
            "from": 52,
            "to": 9           
        }
    ]
}